stencila_types-2.0.0a31.dist-info/METADATA
stencila_types-2.0.0a31.dist-info/WHEEL
stencila_types/__init__.py
stencila_types/shortcuts.py
stencila_types/types.py
stencila_types/utilities.py
stencila_types-2.0.0a31.dist-info/RECORD
